LICENSE
MANIFEST.in
README.md
pytest_polecat.py
setup.py
pytest_polecat.egg-info/PKG-INFO
pytest_polecat.egg-info/SOURCES.txt
pytest_polecat.egg-info/dependency_links.txt
pytest_polecat.egg-info/entry_points.txt
pytest_polecat.egg-info/requires.txt
pytest_polecat.egg-info/top_level.txt